Metadata-Version: 2.1
Name: tralutils
Version: 0.0.4
Summary: Utils for working with videodir archive from video registrator Tral
Home-page: https://github.com/sv99/tralutil
Author: sv99
Author-email: sv99@inbox.ru
License: UNKNOWN
Platform: any
Classifier: Operating System :: OS Independent
Classifier: Programming Language :: Python :: 3
Classifier: Topic :: Utilities
Requires-Python: >=3
Provides-Extra: dev
